qcos/__init__.py
qcos/auth.py
qcos/cli.py
qcos/client.py
qcos/configure.py
qcos-2.3.3.dist-info/LICENSE
qcos-2.3.3.dist-info/METADATA
qcos-2.3.3.dist-info/WHEEL
qcos-2.3.3.dist-info/entry_points.txt
qcos-2.3.3.dist-info/RECORD
