Metadata-Version: 2.1
Name: qcos
Version: 2.3.3
Summary: 腾讯云对象存储库，支持命令行
Home-page: https://github.com/codeif/qcos
License: MIT
Author: codeif
Author-email: me@codeif.com
Requires-Python: >=3.8,<4.0
Classifier: License :: OSI Approved :: MIT License
Classifier: Programming Language :: Python :: 3
Classifier: Programming Language :: Python :: 3.8
Classifier: Programming Language :: Python :: 3.9
Classifier: Programming Language :: Python :: 3.10
Classifier: Programming Language :: Python :: 3.11
Requires-Dist: termcolor (>=2.3.0,<3.0.0)
Project-URL: Repository, https://github.com/codeif/qcos
